README
setup.py
iomock/__init__.py
iomock/disk.py
iomock/os_file.py
iomock.egg-info/PKG-INFO
iomock.egg-info/SOURCES.txt
iomock.egg-info/dependency_links.txt
iomock.egg-info/top_level.txt