Metadata-Version: 1.1
Name: iomock
Version: 0.1
Summary: Python module which provides mock classes that emulate file access methods in os, os.path, glob.
Home-page: https://github.com/MarSik/python-iomock
Author: Martin Sivak
Author-email: msivak@redhat.com
License: GPLv2+
Keywords: mock testing file open os glob
Platform: UNKNOWN
Classifier: Development Status :: 3 - Alpha
Classifier: Intended Audience :: Developers
Classifier: Topic :: Software Development :: Testing
Classifier: License :: OSI Approved :: GNU General Public License v2 or later (GPLv2+)
